Rolling_Imax_Processor/__init__.py
Rolling_Imax_Processor/your_script.py
rolling_imax_processor-0.1.2.dist-info/licenses/License
rolling_imax_processor-0.1.2.dist-info/METADATA
rolling_imax_processor-0.1.2.dist-info/WHEEL
rolling_imax_processor-0.1.2.dist-info/top_level.txt
rolling_imax_processor-0.1.2.dist-info/RECORD
