Metadata-Version: 2.4
Name: Rolling_Imax_Processor
Version: 0.1.2
Summary: Processes raw intensity data stored in a nested Year/Month/Day folder structure. Reads per-minute rainfall breakpoint data (mm/min) from Excel files named dd-mm-yyyy.xlsx. Calculates rolling maximum values for intensity classes I1 to I60 and outputs the results in mm/min.
Author: Akshar Singh Rawat, Dr Sadikul Islam, Dr M Muruganandam
Author-email: aksharrawat1@gmail.com
Classifier: Programming Language :: Python :: 3
Classifier: License :: OSI Approved :: MIT License
Classifier: Operating System :: OS Independent
Requires-Python: >=3.6
License-File: License
Dynamic: author
Dynamic: author-email
Dynamic: classifier
Dynamic: description
Dynamic: description-content-type
Dynamic: license-file
Dynamic: requires-python
Dynamic: summary
